{
  "$schema": "http://json.schemastore.org/sarif-1.0.0",
  "version": "1.0.0",
  "runs": [
    {
      "tool": {
        "name": "Microsoft (R) Visual C# Compiler",
        "version": "5.0.0.0",
        "fileVersion": "5.0.0-2.25612.105 (44525024)",
        "semanticVersion": "5.0.0",
        "language": "en-US"
      },
      "results": [
        {
          "ruleId": "CS8618",
          "level": "warning",
          "message": "Non-nullable property 'Price' must contain a non-null value when exiting constructor. Consider adding the 'required' modifier or declaring the property as nullable.",
          "locations": [
            {
              "resultFile": {
                "uri": "file:///C:/Projects/2026/ata/backend/ArbitrageApi/Services/Exchanges/Coinbase/CoinbaseAdvancedTradeService.cs",
                "region": {
                  "startLine": 459,
                  "startColumn": 18,
                  "endLine": 459,
                  "endColumn": 23
                }
              }
            }
          ],
          "relatedLocations": [
            {
              "physicalLocation": {
                "uri": "file:///C:/Projects/2026/ata/backend/ArbitrageApi/Services/Exchanges/Coinbase/CoinbaseAdvancedTradeService.cs",
                "region": {
                  "startLine": 459,
                  "startColumn": 18,
                  "endLine": 459,
                  "endColumn": 23
                }
              }
            }
          ],
          "properties": {
            "warningLevel": 1
          }
        },
        {
          "ruleId": "CS8618",
          "level": "warning",
          "message": "Non-nullable property 'Size' must contain a non-null value when exiting constructor. Consider adding the 'required' modifier or declaring the property as nullable.",
          "locations": [
            {
              "resultFile": {
                "uri": "file:///C:/Projects/2026/ata/backend/ArbitrageApi/Services/Exchanges/Coinbase/CoinbaseAdvancedTradeService.cs",
                "region": {
                  "startLine": 462,
                  "startColumn": 18,
                  "endLine": 462,
                  "endColumn": 22
                }
              }
            }
          ],
          "relatedLocations": [
            {
              "physicalLocation": {
                "uri": "file:///C:/Projects/2026/ata/backend/ArbitrageApi/Services/Exchanges/Coinbase/CoinbaseAdvancedTradeService.cs",
                "region": {
                  "startLine": 462,
                  "startColumn": 18,
                  "endLine": 462,
                  "endColumn": 22
                }
              }
            }
          ],
          "properties": {
            "warningLevel": 1
          }
        },
        {
          "ruleId": "CS8618",
          "level": "warning",
          "message": "Non-nullable property 'PriceBook' must contain a non-null value when exiting constructor. Consider adding the 'required' modifier or declaring the property as nullable.",
          "locations": [
            {
              "resultFile": {
                "uri": "file:///C:/Projects/2026/ata/backend/ArbitrageApi/Services/Exchanges/Coinbase/CoinbaseAdvancedTradeService.cs",
                "region": {
                  "startLine": 486,
                  "startColumn": 21,
                  "endLine": 486,
                  "endColumn": 30
                }
              }
            }
          ],
          "relatedLocations": [
            {
              "physicalLocation": {
                "uri": "file:///C:/Projects/2026/ata/backend/ArbitrageApi/Services/Exchanges/Coinbase/CoinbaseAdvancedTradeService.cs",
                "region": {
                  "startLine": 486,
                  "startColumn": 21,
                  "endLine": 486,
                  "endColumn": 30
                }
              }
            }
          ],
          "properties": {
            "warningLevel": 1
          }
        },
        {
          "ruleId": "CS8618",
          "level": "warning",
          "message": "Non-nullable property 'ProductId' must contain a non-null value when exiting constructor. Consider adding the 'required' modifier or declaring the property as nullable.",
          "locations": [
            {
              "resultFile": {
                "uri": "file:///C:/Projects/2026/ata/backend/ArbitrageApi/Services/Exchanges/Coinbase/CoinbaseAdvancedTradeService.cs",
                "region": {
                  "startLine": 468,
                  "startColumn": 18,
                  "endLine": 468,
                  "endColumn": 27
                }
              }
            }
          ],
          "relatedLocations": [
            {
              "physicalLocation": {
                "uri": "file:///C:/Projects/2026/ata/backend/ArbitrageApi/Services/Exchanges/Coinbase/CoinbaseAdvancedTradeService.cs",
                "region": {
                  "startLine": 468,
                  "startColumn": 18,
                  "endLine": 468,
                  "endColumn": 27
                }
              }
            }
          ],
          "properties": {
            "warningLevel": 1
          }
        },
        {
          "ruleId": "CS8618",
          "level": "warning",
          "message": "Non-nullable property 'Time' must contain a non-null value when exiting constructor. Consider adding the 'required' modifier or declaring the property as nullable.",
          "locations": [
            {
              "resultFile": {
                "uri": "file:///C:/Projects/2026/ata/backend/ArbitrageApi/Services/Exchanges/Coinbase/CoinbaseAdvancedTradeService.cs",
                "region": {
                  "startLine": 477,
                  "startColumn": 18,
                  "endLine": 477,
                  "endColumn": 22
                }
              }
            }
          ],
          "relatedLocations": [
            {
              "physicalLocation": {
                "uri": "file:///C:/Projects/2026/ata/backend/ArbitrageApi/Services/Exchanges/Coinbase/CoinbaseAdvancedTradeService.cs",
                "region": {
                  "startLine": 477,
                  "startColumn": 18,
                  "endLine": 477,
                  "endColumn": 22
                }
              }
            }
          ],
          "properties": {
            "warningLevel": 1
          }
        },
        {
          "ruleId": "CS8618",
          "level": "warning",
          "message": "Non-nullable property 'Sequence' must contain a non-null value when exiting constructor. Consider adding the 'required' modifier or declaring the property as nullable.",
          "locations": [
            {
              "resultFile": {
                "uri": "file:///C:/Projects/2026/ata/backend/ArbitrageApi/Services/Exchanges/Coinbase/CoinbaseAdvancedTradeService.cs",
                "region": {
                  "startLine": 480,
                  "startColumn": 18,
                  "endLine": 480,
                  "endColumn": 26
                }
              }
            }
          ],
          "relatedLocations": [
            {
              "physicalLocation": {
                "uri": "file:///C:/Projects/2026/ata/backend/ArbitrageApi/Services/Exchanges/Coinbase/CoinbaseAdvancedTradeService.cs",
                "region": {
                  "startLine": 480,
                  "startColumn": 18,
                  "endLine": 480,
                  "endColumn": 26
                }
              }
            }
          ],
          "properties": {
            "warningLevel": 1
          }
        },
        {
          "ruleId": "CS8618",
          "level": "warning",
          "message": "Non-nullable property 'ProductId' must contain a non-null value when exiting constructor. Consider adding the 'required' modifier or declaring the property as nullable.",
          "locations": [
            {
              "resultFile": {
                "uri": "file:///C:/Projects/2026/ata/backend/ArbitrageApi/Services/Exchanges/Coinbase/CoinbaseAdvancedTradeService.cs",
                "region": {
                  "startLine": 492,
                  "startColumn": 18,
                  "endLine": 492,
                  "endColumn": 27
                }
              }
            }
          ],
          "relatedLocations": [
            {
              "physicalLocation": {
                "uri": "file:///C:/Projects/2026/ata/backend/ArbitrageApi/Services/Exchanges/Coinbase/CoinbaseAdvancedTradeService.cs",
                "region": {
                  "startLine": 492,
                  "startColumn": 18,
                  "endLine": 492,
                  "endColumn": 27
                }
              }
            }
          ],
          "properties": {
            "warningLevel": 1
          }
        },
        {
          "ruleId": "CS8618",
          "level": "warning",
          "message": "Non-nullable property 'Time' must contain a non-null value when exiting constructor. Consider adding the 'required' modifier or declaring the property as nullable.",
          "locations": [
            {
              "resultFile": {
                "uri": "file:///C:/Projects/2026/ata/backend/ArbitrageApi/Services/Exchanges/Coinbase/CoinbaseAdvancedTradeService.cs",
                "region": {
                  "startLine": 501,
                  "startColumn": 18,
                  "endLine": 501,
                  "endColumn": 22
                }
              }
            }
          ],
          "relatedLocations": [
            {
              "physicalLocation": {
                "uri": "file:///C:/Projects/2026/ata/backend/ArbitrageApi/Services/Exchanges/Coinbase/CoinbaseAdvancedTradeService.cs",
                "region": {
                  "startLine": 501,
                  "startColumn": 18,
                  "endLine": 501,
                  "endColumn": 22
                }
              }
            }
          ],
          "properties": {
            "warningLevel": 1
          }
        },
        {
          "ruleId": "CS8618",
          "level": "warning",
          "message": "Non-nullable property 'Sequence' must contain a non-null value when exiting constructor. Consider adding the 'required' modifier or declaring the property as nullable.",
          "locations": [
            {
              "resultFile": {
                "uri": "file:///C:/Projects/2026/ata/backend/ArbitrageApi/Services/Exchanges/Coinbase/CoinbaseAdvancedTradeService.cs",
                "region": {
                  "startLine": 504,
                  "startColumn": 18,
                  "endLine": 504,
                  "endColumn": 26
                }
              }
            }
          ],
          "relatedLocations": [
            {
              "physicalLocation": {
                "uri": "file:///C:/Projects/2026/ata/backend/ArbitrageApi/Services/Exchanges/Coinbase/CoinbaseAdvancedTradeService.cs",
                "region": {
                  "startLine": 504,
                  "startColumn": 18,
                  "endLine": 504,
                  "endColumn": 26
                }
              }
            }
          ],
          "properties": {
            "warningLevel": 1
          }
        },
        {
          "ruleId": "CS8618",
          "level": "warning",
          "message": "Non-nullable property 'Products' must contain a non-null value when exiting constructor. Consider adding the 'required' modifier or declaring the property as nullable.",
          "locations": [
            {
              "resultFile": {
                "uri": "file:///C:/Projects/2026/ata/backend/ArbitrageApi/Services/Exchanges/Coinbase/CoinbaseAdvancedTradeService.cs",
                "region": {
                  "startLine": 576,
                  "startColumn": 33,
                  "endLine": 576,
                  "endColumn": 41
                }
              }
            }
          ],
          "relatedLocations": [
            {
              "physicalLocation": {
                "uri": "file:///C:/Projects/2026/ata/backend/ArbitrageApi/Services/Exchanges/Coinbase/CoinbaseAdvancedTradeService.cs",
                "region": {
                  "startLine": 576,
                  "startColumn": 33,
                  "endLine": 576,
                  "endColumn": 41
                }
              }
            }
          ],
          "properties": {
            "warningLevel": 1
          }
        },
        {
          "ruleId": "CS8618",
          "level": "warning",
          "message": "Non-nullable property 'ProductId' must contain a non-null value when exiting constructor. Consider adding the 'required' modifier or declaring the property as nullable.",
          "locations": [
            {
              "resultFile": {
                "uri": "file:///C:/Projects/2026/ata/backend/ArbitrageApi/Services/Exchanges/Coinbase/CoinbaseAdvancedTradeService.cs",
                "region": {
                  "startLine": 557,
                  "startColumn": 18,
                  "endLine": 557,
                  "endColumn": 27
                }
              }
            }
          ],
          "relatedLocations": [
            {
              "physicalLocation": {
                "uri": "file:///C:/Projects/2026/ata/backend/ArbitrageApi/Services/Exchanges/Coinbase/CoinbaseAdvancedTradeService.cs",
                "region": {
                  "startLine": 557,
                  "startColumn": 18,
                  "endLine": 557,
                  "endColumn": 27
                }
              }
            }
          ],
          "properties": {
            "warningLevel": 1
          }
        },
        {
          "ruleId": "CS8618",
          "level": "warning",
          "message": "Non-nullable property 'BaseCurrency' must contain a non-null value when exiting constructor. Consider adding the 'required' modifier or declaring the property as nullable.",
          "locations": [
            {
              "resultFile": {
                "uri": "file:///C:/Projects/2026/ata/backend/ArbitrageApi/Services/Exchanges/Coinbase/CoinbaseAdvancedTradeService.cs",
                "region": {
                  "startLine": 560,
                  "startColumn": 18,
                  "endLine": 560,
                  "endColumn": 30
                }
              }
            }
          ],
          "relatedLocations": [
            {
              "physicalLocation": {
                "uri": "file:///C:/Projects/2026/ata/backend/ArbitrageApi/Services/Exchanges/Coinbase/CoinbaseAdvancedTradeService.cs",
                "region": {
                  "startLine": 560,
                  "startColumn": 18,
                  "endLine": 560,
                  "endColumn": 30
                }
              }
            }
          ],
          "properties": {
            "warningLevel": 1
          }
        },
        {
          "ruleId": "CS8618",
          "level": "warning",
          "message": "Non-nullable property 'QuoteCurrency' must contain a non-null value when exiting constructor. Consider adding the 'required' modifier or declaring the property as nullable.",
          "locations": [
            {
              "resultFile": {
                "uri": "file:///C:/Projects/2026/ata/backend/ArbitrageApi/Services/Exchanges/Coinbase/CoinbaseAdvancedTradeService.cs",
                "region": {
                  "startLine": 563,
                  "startColumn": 18,
                  "endLine": 563,
                  "endColumn": 31
                }
              }
            }
          ],
          "relatedLocations": [
            {
              "physicalLocation": {
                "uri": "file:///C:/Projects/2026/ata/backend/ArbitrageApi/Services/Exchanges/Coinbase/CoinbaseAdvancedTradeService.cs",
                "region": {
                  "startLine": 563,
                  "startColumn": 18,
                  "endLine": 563,
                  "endColumn": 31
                }
              }
            }
          ],
          "properties": {
            "warningLevel": 1
          }
        },
        {
          "ruleId": "CS8618",
          "level": "warning",
          "message": "Non-nullable property 'DisplayName' must contain a non-null value when exiting constructor. Consider adding the 'required' modifier or declaring the property as nullable.",
          "locations": [
            {
              "resultFile": {
                "uri": "file:///C:/Projects/2026/ata/backend/ArbitrageApi/Services/Exchanges/Coinbase/CoinbaseAdvancedTradeService.cs",
                "region": {
                  "startLine": 566,
                  "startColumn": 18,
                  "endLine": 566,
                  "endColumn": 29
                }
              }
            }
          ],
          "relatedLocations": [
            {
              "physicalLocation": {
                "uri": "file:///C:/Projects/2026/ata/backend/ArbitrageApi/Services/Exchanges/Coinbase/CoinbaseAdvancedTradeService.cs",
                "region": {
                  "startLine": 566,
                  "startColumn": 18,
                  "endLine": 566,
                  "endColumn": 29
                }
              }
            }
          ],
          "properties": {
            "warningLevel": 1
          }
        },
        {
          "ruleId": "CS8618",
          "level": "warning",
          "message": "Non-nullable property 'Status' must contain a non-null value when exiting constructor. Consider adding the 'required' modifier or declaring the property as nullable.",
          "locations": [
            {
              "resultFile": {
                "uri": "file:///C:/Projects/2026/ata/backend/ArbitrageApi/Services/Exchanges/Coinbase/CoinbaseAdvancedTradeService.cs",
                "region": {
                  "startLine": 569,
                  "startColumn": 18,
                  "endLine": 569,
                  "endColumn": 24
                }
              }
            }
          ],
          "relatedLocations": [
            {
              "physicalLocation": {
                "uri": "file:///C:/Projects/2026/ata/backend/ArbitrageApi/Services/Exchanges/Coinbase/CoinbaseAdvancedTradeService.cs",
                "region": {
                  "startLine": 569,
                  "startColumn": 18,
                  "endLine": 569,
                  "endColumn": 24
                }
              }
            }
          ],
          "properties": {
            "warningLevel": 1
          }
        },
        {
          "ruleId": "CS8618",
          "level": "warning",
          "message": "Non-nullable property 'Value' must contain a non-null value when exiting constructor. Consider adding the 'required' modifier or declaring the property as nullable.",
          "locations": [
            {
              "resultFile": {
                "uri": "file:///C:/Projects/2026/ata/backend/ArbitrageApi/Services/Exchanges/Coinbase/CoinbaseAdvancedTradeService.cs",
                "region": {
                  "startLine": 633,
                  "startColumn": 18,
                  "endLine": 633,
                  "endColumn": 23
                }
              }
            }
          ],
          "relatedLocations": [
            {
              "physicalLocation": {
                "uri": "file:///C:/Projects/2026/ata/backend/ArbitrageApi/Services/Exchanges/Coinbase/CoinbaseAdvancedTradeService.cs",
                "region": {
                  "startLine": 633,
                  "startColumn": 18,
                  "endLine": 633,
                  "endColumn": 23
                }
              }
            }
          ],
          "properties": {
            "warningLevel": 1
          }
        },
        {
          "ruleId": "CS8618",
          "level": "warning",
          "message": "Non-nullable property 'Currency' must contain a non-null value when exiting constructor. Consider adding the 'required' modifier or declaring the property as nullable.",
          "locations": [
            {
              "resultFile": {
                "uri": "file:///C:/Projects/2026/ata/backend/ArbitrageApi/Services/Exchanges/Coinbase/CoinbaseAdvancedTradeService.cs",
                "region": {
                  "startLine": 636,
                  "startColumn": 18,
                  "endLine": 636,
                  "endColumn": 26
                }
              }
            }
          ],
          "relatedLocations": [
            {
              "physicalLocation": {
                "uri": "file:///C:/Projects/2026/ata/backend/ArbitrageApi/Services/Exchanges/Coinbase/CoinbaseAdvancedTradeService.cs",
                "region": {
                  "startLine": 636,
                  "startColumn": 18,
                  "endLine": 636,
                  "endColumn": 26
                }
              }
            }
          ],
          "properties": {
            "warningLevel": 1
          }
        },
        {
          "ruleId": "CS8618",
          "level": "warning",
          "message": "Non-nullable property 'Uuid' must contain a non-null value when exiting constructor. Consider adding the 'required' modifier or declaring the property as nullable.",
          "locations": [
            {
              "resultFile": {
                "uri": "file:///C:/Projects/2026/ata/backend/ArbitrageApi/Services/Exchanges/Coinbase/CoinbaseAdvancedTradeService.cs",
                "region": {
                  "startLine": 585,
                  "startColumn": 18,
                  "endLine": 585,
                  "endColumn": 22
                }
              }
            }
          ],
          "relatedLocations": [
            {
              "physicalLocation": {
                "uri": "file:///C:/Projects/2026/ata/backend/ArbitrageApi/Services/Exchanges/Coinbase/CoinbaseAdvancedTradeService.cs",
                "region": {
                  "startLine": 585,
                  "startColumn": 18,
                  "endLine": 585,
                  "endColumn": 22
                }
              }
            }
          ],
          "properties": {
            "warningLevel": 1
          }
        },
        {
          "ruleId": "CS8618",
          "level": "warning",
          "message": "Non-nullable property 'Name' must contain a non-null value when exiting constructor. Consider adding the 'required' modifier or declaring the property as nullable.",
          "locations": [
            {
              "resultFile": {
                "uri": "file:///C:/Projects/2026/ata/backend/ArbitrageApi/Services/Exchanges/Coinbase/CoinbaseAdvancedTradeService.cs",
                "region": {
                  "startLine": 588,
                  "startColumn": 18,
                  "endLine": 588,
                  "endColumn": 22
                }
              }
            }
          ],
          "relatedLocations": [
            {
              "physicalLocation": {
                "uri": "file:///C:/Projects/2026/ata/backend/ArbitrageApi/Services/Exchanges/Coinbase/CoinbaseAdvancedTradeService.cs",
                "region": {
                  "startLine": 588,
                  "startColumn": 18,
                  "endLine": 588,
                  "endColumn": 22
                }
              }
            }
          ],
          "properties": {
            "warningLevel": 1
          }
        },
        {
          "ruleId": "CS8618",
          "level": "warning",
          "message": "Non-nullable property 'Currency' must contain a non-null value when exiting constructor. Consider adding the 'required' modifier or declaring the property as nullable.",
          "locations": [
            {
              "resultFile": {
                "uri": "file:///C:/Projects/2026/ata/backend/ArbitrageApi/Services/Exchanges/Coinbase/CoinbaseAdvancedTradeService.cs",
                "region": {
                  "startLine": 591,
                  "startColumn": 18,
                  "endLine": 591,
                  "endColumn": 26
                }
              }
            }
          ],
          "relatedLocations": [
            {
              "physicalLocation": {
                "uri": "file:///C:/Projects/2026/ata/backend/ArbitrageApi/Services/Exchanges/Coinbase/CoinbaseAdvancedTradeService.cs",
                "region": {
                  "startLine": 591,
                  "startColumn": 18,
                  "endLine": 591,
                  "endColumn": 26
                }
              }
            }
          ],
          "properties": {
            "warningLevel": 1
          }
        },
        {
          "ruleId": "CS8618",
          "level": "warning",
          "message": "Non-nullable property 'AvailableBalance' must contain a non-null value when exiting constructor. Consider adding the 'required' modifier or declaring the property as nullable.",
          "locations": [
            {
              "resultFile": {
                "uri": "file:///C:/Projects/2026/ata/backend/ArbitrageApi/Services/Exchanges/Coinbase/CoinbaseAdvancedTradeService.cs",
                "region": {
                  "startLine": 594,
                  "startColumn": 28,
                  "endLine": 594,
                  "endColumn": 44
                }
              }
            }
          ],
          "relatedLocations": [
            {
              "physicalLocation": {
                "uri": "file:///C:/Projects/2026/ata/backend/ArbitrageApi/Services/Exchanges/Coinbase/CoinbaseAdvancedTradeService.cs",
                "region": {
                  "startLine": 594,
                  "startColumn": 28,
                  "endLine": 594,
                  "endColumn": 44
                }
              }
            }
          ],
          "properties": {
            "warningLevel": 1
          }
        },
        {
          "ruleId": "CS8618",
          "level": "warning",
          "message": "Non-nullable property 'Type' must contain a non-null value when exiting constructor. Consider adding the 'required' modifier or declaring the property as nullable.",
          "locations": [
            {
              "resultFile": {
                "uri": "file:///C:/Projects/2026/ata/backend/ArbitrageApi/Services/Exchanges/Coinbase/CoinbaseAdvancedTradeService.cs",
                "region": {
                  "startLine": 612,
                  "startColumn": 18,
                  "endLine": 612,
                  "endColumn": 22
                }
              }
            }
          ],
          "relatedLocations": [
            {
              "physicalLocation": {
                "uri": "file:///C:/Projects/2026/ata/backend/ArbitrageApi/Services/Exchanges/Coinbase/CoinbaseAdvancedTradeService.cs",
                "region": {
                  "startLine": 612,
                  "startColumn": 18,
                  "endLine": 612,
                  "endColumn": 22
                }
              }
            }
          ],
          "properties": {
            "warningLevel": 1
          }
        },
        {
          "ruleId": "CS8618",
          "level": "warning",
          "message": "Non-nullable property 'Hold' must contain a non-null value when exiting constructor. Consider adding the 'required' modifier or declaring the property as nullable.",
          "locations": [
            {
              "resultFile": {
                "uri": "file:///C:/Projects/2026/ata/backend/ArbitrageApi/Services/Exchanges/Coinbase/CoinbaseAdvancedTradeService.cs",
                "region": {
                  "startLine": 618,
                  "startColumn": 16,
                  "endLine": 618,
                  "endColumn": 20
                }
              }
            }
          ],
          "relatedLocations": [
            {
              "physicalLocation": {
                "uri": "file:///C:/Projects/2026/ata/backend/ArbitrageApi/Services/Exchanges/Coinbase/CoinbaseAdvancedTradeService.cs",
                "region": {
                  "startLine": 618,
                  "startColumn": 16,
                  "endLine": 618,
                  "endColumn": 20
                }
              }
            }
          ],
          "properties": {
            "warningLevel": 1
          }
        },
        {
          "ruleId": "CS8618",
          "level": "warning",
          "message": "Non-nullable property 'Value' must contain a non-null value when exiting constructor. Consider adding the 'required' modifier or declaring the property as nullable.",
          "locations": [
            {
              "resultFile": {
                "uri": "file:///C:/Projects/2026/ata/backend/ArbitrageApi/Services/Exchanges/Coinbase/CoinbaseAdvancedTradeService.cs",
                "region": {
                  "startLine": 624,
                  "startColumn": 18,
                  "endLine": 624,
                  "endColumn": 23
                }
              }
            }
          ],
          "relatedLocations": [
            {
              "physicalLocation": {
                "uri": "file:///C:/Projects/2026/ata/backend/ArbitrageApi/Services/Exchanges/Coinbase/CoinbaseAdvancedTradeService.cs",
                "region": {
                  "startLine": 624,
                  "startColumn": 18,
                  "endLine": 624,
                  "endColumn": 23
                }
              }
            }
          ],
          "properties": {
            "warningLevel": 1
          }
        },
        {
          "ruleId": "CS8618",
          "level": "warning",
          "message": "Non-nullable property 'Currency' must contain a non-null value when exiting constructor. Consider adding the 'required' modifier or declaring the property as nullable.",
          "locations": [
            {
              "resultFile": {
                "uri": "file:///C:/Projects/2026/ata/backend/ArbitrageApi/Services/Exchanges/Coinbase/CoinbaseAdvancedTradeService.cs",
                "region": {
                  "startLine": 627,
                  "startColumn": 18,
                  "endLine": 627,
                  "endColumn": 26
                }
              }
            }
          ],
          "relatedLocations": [
            {
              "physicalLocation": {
                "uri": "file:///C:/Projects/2026/ata/backend/ArbitrageApi/Services/Exchanges/Coinbase/CoinbaseAdvancedTradeService.cs",
                "region": {
                  "startLine": 627,
                  "startColumn": 18,
                  "endLine": 627,
                  "endColumn": 26
                }
              }
            }
          ],
          "properties": {
            "warningLevel": 1
          }
        },
        {
          "ruleId": "CS8618",
          "level": "warning",
          "message": "Non-nullable property 'ArbitrageEvents' must contain a non-null value when exiting constructor. Consider adding the 'required' modifier or declaring the property as nullable.",
          "suppressionStates": [
            "suppressedInSource"
          ],
          "locations": [
            {
              "resultFile": {
                "uri": "file:///C:/Projects/2026/ata/backend/ArbitrageApi/Data/StatsDbContext.cs",
                "region": {
                  "startLine": 8,
                  "startColumn": 12,
                  "endLine": 8,
                  "endColumn": 26
                }
              }
            }
          ],
          "relatedLocations": [
            {
              "physicalLocation": {
                "uri": "file:///C:/Projects/2026/ata/backend/ArbitrageApi/Data/StatsDbContext.cs",
                "region": {
                  "startLine": 12,
                  "startColumn": 34,
                  "endLine": 12,
                  "endColumn": 49
                }
              }
            }
          ],
          "properties": {
            "warningLevel": 1
          }
        },
        {
          "ruleId": "CS1061",
          "level": "error",
          "message": "'DbContextOptionsBuilder' does not contain a definition for 'UseSqlite' and no accessible extension method 'UseSqlite' accepting a first argument of type 'DbContextOptionsBuilder' could be found (are you missing a using directive or an assembly reference?)",
          "locations": [
            {
              "resultFile": {
                "uri": "file:///C:/Projects/2026/ata/backend/ArbitrageApi/Program.cs",
                "region": {
                  "startLine": 15,
                  "startColumn": 13,
                  "endLine": 15,
                  "endColumn": 22
                }
              }
            }
          ]
        },
        {
          "ruleId": "SYSLIB0023",
          "level": "warning",
          "message": "'RNGCryptoServiceProvider' is obsolete: 'RNGCryptoServiceProvider is obsolete. To generate a random number, use one of the RandomNumberGenerator static methods instead.'",
          "locations": [
            {
              "resultFile": {
                "uri": "file:///C:/Projects/2026/ata/backend/ArbitrageApi/Services/Exchanges/Coinbase/CoinbaseAdvancedTradeService.cs",
                "region": {
                  "startLine": 137,
                  "startColumn": 31,
                  "endLine": 137,
                  "endColumn": 55
                }
              }
            }
          ],
          "properties": {
            "warningLevel": 2
          }
        },
        {
          "ruleId": "CS8603",
          "level": "warning",
          "message": "Possible null reference return.",
          "locations": [
            {
              "resultFile": {
                "uri": "file:///C:/Projects/2026/ata/backend/ArbitrageApi/Services/Exchanges/Coinbase/CoinbaseAdvancedTradeService.cs",
                "region": {
                  "startLine": 290,
                  "startColumn": 20,
                  "endLine": 290,
                  "endColumn": 29
                }
              }
            }
          ],
          "properties": {
            "warningLevel": 1
          }
        },
        {
          "ruleId": "CS8603",
          "level": "warning",
          "message": "Possible null reference return.",
          "locations": [
            {
              "resultFile": {
                "uri": "file:///C:/Projects/2026/ata/backend/ArbitrageApi/Services/Exchanges/Coinbase/CoinbaseAdvancedTradeService.cs",
                "region": {
                  "startLine": 366,
                  "startColumn": 26,
                  "endLine": 366,
                  "endColumn": 79
                }
              }
            }
          ],
          "properties": {
            "warningLevel": 1
          }
        },
        {
          "ruleId": "CS8603",
          "level": "warning",
          "message": "Possible null reference return.",
          "locations": [
            {
              "resultFile": {
                "uri": "file:///C:/Projects/2026/ata/backend/ArbitrageApi/Services/Exchanges/Coinbase/CoinbaseAdvancedTradeService.cs",
                "region": {
                  "startLine": 402,
                  "startColumn": 26,
                  "endLine": 402,
                  "endColumn": 114
                }
              }
            }
          ],
          "properties": {
            "warningLevel": 1
          }
        },
        {
          "ruleId": "CA1050",
          "level": "note",
          "message": "Declare types in namespaces",
          "locations": [
            {
              "resultFile": {
                "uri": "file:///C:/Projects/2026/ata/backend/ArbitrageApi/Services/Exchanges/CdpAuth.cs",
                "region": {
                  "startLine": 9,
                  "startColumn": 21,
                  "endLine": 9,
                  "endColumn": 28
                }
              }
            }
          ],
          "properties": {
            "warningLevel": 1
          }
        },
        {
          "ruleId": "CA1050",
          "level": "note",
          "message": "Declare types in namespaces",
          "locations": [
            {
              "resultFile": {
                "uri": "file:///C:/Projects/2026/ata/backend/ArbitrageApi/Services/Exchanges/Coinbase/CoinbaseAdvancedTradeService.cs",
                "region": {
                  "startLine": 456,
                  "startColumn": 14,
                  "endLine": 456,
                  "endColumn": 28
                }
              }
            }
          ],
          "properties": {
            "warningLevel": 1
          }
        },
        {
          "ruleId": "CA1050",
          "level": "note",
          "message": "Declare types in namespaces",
          "locations": [
            {
              "resultFile": {
                "uri": "file:///C:/Projects/2026/ata/backend/ArbitrageApi/Services/Exchanges/Coinbase/CoinbaseAdvancedTradeService.cs",
                "region": {
                  "startLine": 465,
                  "startColumn": 14,
                  "endLine": 465,
                  "endColumn": 23
                }
              }
            }
          ],
          "properties": {
            "warningLevel": 1
          }
        },
        {
          "ruleId": "CA1050",
          "level": "note",
          "message": "Declare types in namespaces",
          "locations": [
            {
              "resultFile": {
                "uri": "file:///C:/Projects/2026/ata/backend/ArbitrageApi/Services/Exchanges/Coinbase/CoinbaseAdvancedTradeService.cs",
                "region": {
                  "startLine": 483,
                  "startColumn": 14,
                  "endLine": 483,
                  "endColumn": 33
                }
              }
            }
          ],
          "properties": {
            "warningLevel": 1
          }
        },
        {
          "ruleId": "CA1050",
          "level": "note",
          "message": "Declare types in namespaces",
          "locations": [
            {
              "resultFile": {
                "uri": "file:///C:/Projects/2026/ata/backend/ArbitrageApi/Services/Exchanges/Coinbase/CoinbaseAdvancedTradeService.cs",
                "region": {
                  "startLine": 513,
                  "startColumn": 14,
                  "endLine": 513,
                  "endColumn": 35
                }
              }
            }
          ],
          "properties": {
            "warningLevel": 1
          }
        },
        {
          "ruleId": "CA1050",
          "level": "note",
          "message": "Declare types in namespaces",
          "locations": [
            {
              "resultFile": {
                "uri": "file:///C:/Projects/2026/ata/backend/ArbitrageApi/Services/Exchanges/Coinbase/CoinbaseAdvancedTradeService.cs",
                "region": {
                  "startLine": 489,
                  "startColumn": 14,
                  "endLine": 489,
                  "endColumn": 39
                }
              }
            }
          ],
          "properties": {
            "warningLevel": 1
          }
        },
        {
          "ruleId": "CA1050",
          "level": "note",
          "message": "Declare types in namespaces",
          "locations": [
            {
              "resultFile": {
                "uri": "file:///C:/Projects/2026/ata/backend/ArbitrageApi/Services/Exchanges/Coinbase/CoinbaseAdvancedTradeService.cs",
                "region": {
                  "startLine": 519,
                  "startColumn": 14,
                  "endLine": 519,
                  "endColumn": 31
                }
              }
            }
          ],
          "properties": {
            "warningLevel": 1
          }
        },
        {
          "ruleId": "CA1050",
          "level": "note",
          "message": "Declare types in namespaces",
          "locations": [
            {
              "resultFile": {
                "uri": "file:///C:/Projects/2026/ata/backend/ArbitrageApi/Services/Exchanges/Coinbase/CoinbaseAdvancedTradeService.cs",
                "region": {
                  "startLine": 525,
                  "startColumn": 14,
                  "endLine": 525,
                  "endColumn": 36
                }
              }
            }
          ],
          "properties": {
            "warningLevel": 1
          }
        },
        {
          "ruleId": "CA1050",
          "level": "note",
          "message": "Declare types in namespaces",
          "locations": [
            {
              "resultFile": {
                "uri": "file:///C:/Projects/2026/ata/backend/ArbitrageApi/Services/Exchanges/Coinbase/CoinbaseAdvancedTradeService.cs",
                "region": {
                  "startLine": 507,
                  "startColumn": 14,
                  "endLine": 507,
                  "endColumn": 28
                }
              }
            }
          ],
          "properties": {
            "warningLevel": 1
          }
        },
        {
          "ruleId": "CA1050",
          "level": "note",
          "message": "Declare types in namespaces",
          "locations": [
            {
              "resultFile": {
                "uri": "file:///C:/Projects/2026/ata/backend/ArbitrageApi/Services/Exchanges/Coinbase/CoinbaseAdvancedTradeService.cs",
                "region": {
                  "startLine": 531,
                  "startColumn": 14,
                  "endLine": 531,
                  "endColumn": 33
                }
              }
            }
          ],
          "properties": {
            "warningLevel": 1
          }
        },
        {
          "ruleId": "CA1050",
          "level": "note",
          "message": "Declare types in namespaces",
          "locations": [
            {
              "resultFile": {
                "uri": "file:///C:/Projects/2026/ata/backend/ArbitrageApi/Services/Exchanges/Coinbase/CoinbaseAdvancedTradeService.cs",
                "region": {
                  "startLine": 537,
                  "startColumn": 14,
                  "endLine": 537,
                  "endColumn": 29
                }
              }
            }
          ],
          "properties": {
            "warningLevel": 1
          }
        },
        {
          "ruleId": "CA1050",
          "level": "note",
          "message": "Declare types in namespaces",
          "locations": [
            {
              "resultFile": {
                "uri": "file:///C:/Projects/2026/ata/backend/ArbitrageApi/Services/Exchanges/Coinbase/CoinbaseAdvancedTradeService.cs",
                "region": {
                  "startLine": 554,
                  "startColumn": 14,
                  "endLine": 554,
                  "endColumn": 29
                }
              }
            }
          ],
          "properties": {
            "warningLevel": 1
          }
        },
        {
          "ruleId": "CA1050",
          "level": "note",
          "message": "Declare types in namespaces",
          "locations": [
            {
              "resultFile": {
                "uri": "file:///C:/Projects/2026/ata/backend/ArbitrageApi/Services/Exchanges/Coinbase/CoinbaseAdvancedTradeService.cs",
                "region": {
                  "startLine": 545,
                  "startColumn": 14,
                  "endLine": 545,
                  "endColumn": 41
                }
              }
            }
          ],
          "properties": {
            "warningLevel": 1
          }
        },
        {
          "ruleId": "CA1050",
          "level": "note",
          "message": "Declare types in namespaces",
          "locations": [
            {
              "resultFile": {
                "uri": "file:///C:/Projects/2026/ata/backend/ArbitrageApi/Services/Exchanges/Coinbase/CoinbaseAdvancedTradeService.cs",
                "region": {
                  "startLine": 582,
                  "startColumn": 14,
                  "endLine": 582,
                  "endColumn": 21
                }
              }
            }
          ],
          "properties": {
            "warningLevel": 1
          }
        },
        {
          "ruleId": "CA1050",
          "level": "note",
          "message": "Declare types in namespaces",
          "locations": [
            {
              "resultFile": {
                "uri": "file:///C:/Projects/2026/ata/backend/ArbitrageApi/Services/Exchanges/Coinbase/CoinbaseAdvancedTradeService.cs",
                "region": {
                  "startLine": 630,
                  "startColumn": 14,
                  "endLine": 630,
                  "endColumn": 18
                }
              }
            }
          ],
          "properties": {
            "warningLevel": 1
          }
        },
        {
          "ruleId": "CA1050",
          "level": "note",
          "message": "Declare types in namespaces",
          "locations": [
            {
              "resultFile": {
                "uri": "file:///C:/Projects/2026/ata/backend/ArbitrageApi/Services/Exchanges/Coinbase/CoinbaseAdvancedTradeService.cs",
                "region": {
                  "startLine": 639,
                  "startColumn": 14,
                  "endLine": 639,
                  "endColumn": 30
                }
              }
            }
          ],
          "properties": {
            "warningLevel": 1
          }
        },
        {
          "ruleId": "CA1050",
          "level": "note",
          "message": "Declare types in namespaces",
          "locations": [
            {
              "resultFile": {
                "uri": "file:///C:/Projects/2026/ata/backend/ArbitrageApi/Services/Exchanges/Coinbase/CoinbaseAdvancedTradeService.cs",
                "region": {
                  "startLine": 621,
                  "startColumn": 14,
                  "endLine": 621,
                  "endColumn": 30
                }
              }
            }
          ],
          "properties": {
            "warningLevel": 1
          }
        },
        {
          "ruleId": "CA1050",
          "level": "note",
          "message": "Declare types in namespaces",
          "locations": [
            {
              "resultFile": {
                "uri": "file:///C:/Projects/2026/ata/backend/ArbitrageApi/Services/Exchanges/Coinbase/CoinbaseAdvancedTradeService.cs",
                "region": {
                  "startLine": 573,
                  "startColumn": 14,
                  "endLine": 573,
                  "endColumn": 30
                }
              }
            }
          ],
          "properties": {
            "warningLevel": 1
          }
        },
        {
          "ruleId": "CA1873",
          "level": "note",
          "message": "Evaluation of this argument may be expensive and unnecessary if logging is disabled",
          "locations": [
            {
              "resultFile": {
                "uri": "file:///C:/Projects/2026/ata/backend/ArbitrageApi/Controllers/BalancesController.cs",
                "region": {
                  "startLine": 23,
                  "startColumn": 9,
                  "endLine": 23,
                  "endColumn": 143
                }
              }
            }
          ],
          "properties": {
            "warningLevel": 1
          }
        },
        {
          "ruleId": "CA1873",
          "level": "note",
          "message": "Evaluation of this argument may be expensive and unnecessary if logging is disabled",
          "locations": [
            {
              "resultFile": {
                "uri": "file:///C:/Projects/2026/ata/backend/ArbitrageApi/Services/TradeService.cs",
                "region": {
                  "startLine": 33,
                  "startColumn": 9,
                  "endLine": 33,
                  "endColumn": 136
                }
              }
            }
          ],
          "properties": {
            "warningLevel": 1
          }
        },
        {
          "ruleId": "CA1873",
          "level": "note",
          "message": "Evaluation of this argument may be expensive and unnecessary if logging is disabled",
          "locations": [
            {
              "resultFile": {
                "uri": "file:///C:/Projects/2026/ata/backend/ArbitrageApi/Services/TradeService.cs",
                "region": {
                  "startLine": 51,
                  "startColumn": 9,
                  "endLine": 51,
                  "endColumn": 93
                }
              }
            }
          ],
          "properties": {
            "warningLevel": 1
          }
        },
        {
          "ruleId": "CA1873",
          "level": "note",
          "message": "Evaluation of this argument may be expensive and unnecessary if logging is disabled",
          "locations": [
            {
              "resultFile": {
                "uri": "file:///C:/Projects/2026/ata/backend/ArbitrageApi/Services/TradeService.cs",
                "region": {
                  "startLine": 61,
                  "startColumn": 9,
                  "endLine": 61,
                  "endColumn": 86
                }
              }
            }
          ],
          "properties": {
            "warningLevel": 1
          }
        },
        {
          "ruleId": "CA1873",
          "level": "note",
          "message": "Evaluation of this argument may be expensive and unnecessary if logging is disabled",
          "locations": [
            {
              "resultFile": {
                "uri": "file:///C:/Projects/2026/ata/backend/ArbitrageApi/Services/TradeService.cs",
                "region": {
                  "startLine": 39,
                  "startColumn": 13,
                  "endLine": 39,
                  "endColumn": 99
                }
              }
            }
          ],
          "properties": {
            "warningLevel": 1
          }
        },
        {
          "ruleId": "CA1873",
          "level": "note",
          "message": "Evaluation of this argument may be expensive and unnecessary if logging is disabled",
          "locations": [
            {
              "resultFile": {
                "uri": "file:///C:/Projects/2026/ata/backend/ArbitrageApi/Services/TradeService.cs",
                "region": {
                  "startLine": 71,
                  "startColumn": 9,
                  "endLine": 71,
                  "endColumn": 81
                }
              }
            }
          ],
          "properties": {
            "warningLevel": 1
          }
        },
        {
          "ruleId": "CA1860",
          "level": "note",
          "message": "Prefer comparing 'Count' to 0 rather than using 'Any()', both for clarity and for performance",
          "locations": [
            {
              "resultFile": {
                "uri": "file:///C:/Projects/2026/ata/backend/ArbitrageApi/Controllers/ArbitrageController.cs",
                "region": {
                  "startLine": 51,
                  "startColumn": 43,
                  "endLine": 51,
                  "endColumn": 62
                }
              }
            }
          ],
          "properties": {
            "warningLevel": 1,
            "customProperties": {
              "DiagnosticPropertyKey": "Count"
            }
          }
        },
        {
          "ruleId": "CA1873",
          "level": "note",
          "message": "Evaluation of this argument may be expensive and unnecessary if logging is disabled",
          "locations": [
            {
              "resultFile": {
                "uri": "file:///C:/Projects/2026/ata/backend/ArbitrageApi/Services/TradeService.cs",
                "region": {
                  "startLine": 78,
                  "startColumn": 13,
                  "endLine": 78,
                  "endColumn": 138
                }
              }
            }
          ],
          "properties": {
            "warningLevel": 1
          }
        },
        {
          "ruleId": "CA1873",
          "level": "note",
          "message": "Evaluation of this argument may be expensive and unnecessary if logging is disabled",
          "locations": [
            {
              "resultFile": {
                "uri": "file:///C:/Projects/2026/ata/backend/ArbitrageApi/Services/TradeService.cs",
                "region": {
                  "startLine": 101,
                  "startColumn": 17,
                  "endLine": 101,
                  "endColumn": 157
                }
              }
            }
          ],
          "properties": {
            "warningLevel": 1
          }
        },
        {
          "ruleId": "CA1873",
          "level": "note",
          "message": "Evaluation of this argument may be expensive and unnecessary if logging is disabled",
          "locations": [
            {
              "resultFile": {
                "uri": "file:///C:/Projects/2026/ata/backend/ArbitrageApi/Services/TradeService.cs",
                "region": {
                  "startLine": 136,
                  "startColumn": 9,
                  "endLine": 136,
                  "endColumn": 186
                }
              }
            }
          ],
          "properties": {
            "warningLevel": 1
          }
        },
        {
          "ruleId": "CA1873",
          "level": "note",
          "message": "Evaluation of this argument may be expensive and unnecessary if logging is disabled",
          "locations": [
            {
              "resultFile": {
                "uri": "file:///C:/Projects/2026/ata/backend/ArbitrageApi/Services/TradeService.cs",
                "region": {
                  "startLine": 143,
                  "startColumn": 13,
                  "endLine": 143,
                  "endColumn": 186
                }
              }
            }
          ],
          "properties": {
            "warningLevel": 1
          }
        },
        {
          "ruleId": "CA1873",
          "level": "note",
          "message": "Evaluation of this argument may be expensive and unnecessary if logging is disabled",
          "locations": [
            {
              "resultFile": {
                "uri": "file:///C:/Projects/2026/ata/backend/ArbitrageApi/Services/TradeService.cs",
                "region": {
                  "startLine": 156,
                  "startColumn": 9,
                  "endLine": 156,
                  "endColumn": 110
                }
              }
            }
          ],
          "properties": {
            "warningLevel": 1
          }
        },
        {
          "ruleId": "CA1873",
          "level": "note",
          "message": "Evaluation of this argument may be expensive and unnecessary if logging is disabled",
          "locations": [
            {
              "resultFile": {
                "uri": "file:///C:/Projects/2026/ata/backend/ArbitrageApi/Services/ArbitrageDetectionService.cs",
                "region": {
                  "startLine": 49,
                  "startColumn": 9,
                  "endLine": 49,
                  "endColumn": 125
                }
              }
            }
          ],
          "properties": {
            "warningLevel": 1
          }
        },
        {
          "ruleId": "CA1873",
          "level": "note",
          "message": "Evaluation of this argument may be expensive and unnecessary if logging is disabled",
          "locations": [
            {
              "resultFile": {
                "uri": "file:///C:/Projects/2026/ata/backend/ArbitrageApi/Services/ArbitrageDetectionService.cs",
                "region": {
                  "startLine": 50,
                  "startColumn": 9,
                  "endLine": 51,
                  "endColumn": 77
                }
              }
            }
          ],
          "properties": {
            "warningLevel": 1
          }
        },
        {
          "ruleId": "CA1873",
          "level": "note",
          "message": "Evaluation of this argument may be expensive and unnecessary if logging is disabled",
          "locations": [
            {
              "resultFile": {
                "uri": "file:///C:/Projects/2026/ata/backend/ArbitrageApi/Services/ArbitrageDetectionService.cs",
                "region": {
                  "startLine": 92,
                  "startColumn": 25,
                  "endLine": 92,
                  "endColumn": 150
                }
              }
            }
          ],
          "properties": {
            "warningLevel": 1
          }
        },
        {
          "ruleId": "CA1873",
          "level": "note",
          "message": "Evaluation of this argument may be expensive and unnecessary if logging is disabled",
          "locations": [
            {
              "resultFile": {
                "uri": "file:///C:/Projects/2026/ata/backend/ArbitrageApi/Services/ArbitrageDetectionService.cs",
                "region": {
                  "startLine": 101,
                  "startColumn": 21,
                  "endLine": 109,
                  "endColumn": 54
                }
              }
            }
          ],
          "properties": {
            "warningLevel": 1
          }
        },
        {
          "ruleId": "CA1873",
          "level": "note",
          "message": "Evaluation of this argument may be expensive and unnecessary if logging is disabled",
          "locations": [
            {
              "resultFile": {
                "uri": "file:///C:/Projects/2026/ata/backend/ArbitrageApi/Services/StatePersistenceService.cs",
                "region": {
                  "startLine": 34,
                  "startColumn": 13,
                  "endLine": 34,
                  "endColumn": 89
                }
              }
            }
          ],
          "properties": {
            "warningLevel": 1
          }
        },
        {
          "ruleId": "CA1869",
          "level": "note",
          "message": "Avoid creating a new 'JsonSerializerOptions' instance for every serialization operation. Cache and reuse instances instead.",
          "locations": [
            {
              "resultFile": {
                "uri": "file:///C:/Projects/2026/ata/backend/ArbitrageApi/Services/StatePersistenceService.cs",
                "region": {
                  "startLine": 32,
                  "startColumn": 56,
                  "endLine": 32,
                  "endColumn": 106
                }
              }
            }
          ],
          "properties": {
            "warningLevel": 1
          }
        },
        {
          "ruleId": "CA1873",
          "level": "note",
          "message": "Evaluation of this argument may be expensive and unnecessary if logging is disabled",
          "locations": [
            {
              "resultFile": {
                "uri": "file:///C:/Projects/2026/ata/backend/ArbitrageApi/Services/Exchanges/Coinbase/CoinbaseSandboxState.cs",
                "region": {
                  "startLine": 100,
                  "startColumn": 9,
                  "endLine": 100,
                  "endColumn": 113
                }
              }
            }
          ],
          "properties": {
            "warningLevel": 1
          }
        },
        {
          "ruleId": "CA1873",
          "level": "note",
          "message": "Evaluation of this argument may be expensive and unnecessary if logging is disabled",
          "locations": [
            {
              "resultFile": {
                "uri": "file:///C:/Projects/2026/ata/backend/ArbitrageApi/Services/Exchanges/Binance/BinanceClient.cs",
                "region": {
                  "startLine": 41,
                  "startColumn": 9,
                  "endLine": 41,
                  "endColumn": 96
                }
              }
            }
          ],
          "properties": {
            "warningLevel": 1
          }
        },
        {
          "ruleId": "CA1873",
          "level": "note",
          "message": "Evaluation of this argument may be expensive and unnecessary if logging is disabled",
          "locations": [
            {
              "resultFile": {
                "uri": "file:///C:/Projects/2026/ata/backend/ArbitrageApi/Services/Exchanges/Binance/BinanceBaseState.cs",
                "region": {
                  "startLine": 30,
                  "startColumn": 9,
                  "endLine": 30,
                  "endColumn": 66
                }
              }
            }
          ],
          "properties": {
            "warningLevel": 1
          }
        },
        {
          "ruleId": "CA1873",
          "level": "note",
          "message": "Evaluation of this argument may be expensive and unnecessary if logging is disabled",
          "locations": [
            {
              "resultFile": {
                "uri": "file:///C:/Projects/2026/ata/backend/ArbitrageApi/Services/Exchanges/Coinbase/CoinbaseSandboxState.cs",
                "region": {
                  "startLine": 106,
                  "startColumn": 9,
                  "endLine": 106,
                  "endColumn": 119
                }
              }
            }
          ],
          "properties": {
            "warningLevel": 1
          }
        },
        {
          "ruleId": "CA1873",
          "level": "note",
          "message": "Evaluation of this argument may be expensive and unnecessary if logging is disabled",
          "locations": [
            {
              "resultFile": {
                "uri": "file:///C:/Projects/2026/ata/backend/ArbitrageApi/Services/ArbitrageDetectionService.cs",
                "region": {
                  "startLine": 173,
                  "startColumn": 13,
                  "endLine": 173,
                  "endColumn": 116
                }
              }
            }
          ],
          "properties": {
            "warningLevel": 1
          }
        },
        {
          "ruleId": "CA1873",
          "level": "note",
          "message": "Evaluation of this argument may be expensive and unnecessary if logging is disabled",
          "locations": [
            {
              "resultFile": {
                "uri": "file:///C:/Projects/2026/ata/backend/ArbitrageApi/Services/Exchanges/Coinbase/CoinbaseSandboxState.cs",
                "region": {
                  "startLine": 139,
                  "startColumn": 9,
                  "endLine": 139,
                  "endColumn": 120
                }
              }
            }
          ],
          "properties": {
            "warningLevel": 1
          }
        },
        {
          "ruleId": "CA1873",
          "level": "note",
          "message": "Evaluation of this argument may be expensive and unnecessary if logging is disabled",
          "locations": [
            {
              "resultFile": {
                "uri": "file:///C:/Projects/2026/ata/backend/ArbitrageApi/Services/Exchanges/Binance/BinanceSandboxState.cs",
                "region": {
                  "startLine": 45,
                  "startColumn": 9,
                  "endLine": 45,
                  "endColumn": 113
                }
              }
            }
          ],
          "properties": {
            "warningLevel": 1
          }
        },
        {
          "ruleId": "CA1873",
          "level": "note",
          "message": "Evaluation of this argument may be expensive and unnecessary if logging is disabled",
          "locations": [
            {
              "resultFile": {
                "uri": "file:///C:/Projects/2026/ata/backend/ArbitrageApi/Services/TradeService.cs",
                "region": {
                  "startLine": 177,
                  "startColumn": 13,
                  "endLine": 177,
                  "endColumn": 114
                }
              }
            }
          ],
          "properties": {
            "warningLevel": 1
          }
        },
        {
          "ruleId": "CA1873",
          "level": "note",
          "message": "Evaluation of this argument may be expensive and unnecessary if logging is disabled",
          "locations": [
            {
              "resultFile": {
                "uri": "file:///C:/Projects/2026/ata/backend/ArbitrageApi/Services/TradeService.cs",
                "region": {
                  "startLine": 185,
                  "startColumn": 13,
                  "endLine": 185,
                  "endColumn": 162
                }
              }
            }
          ],
          "properties": {
            "warningLevel": 1
          }
        },
        {
          "ruleId": "CA1873",
          "level": "note",
          "message": "Evaluation of this argument may be expensive and unnecessary if logging is disabled",
          "locations": [
            {
              "resultFile": {
                "uri": "file:///C:/Projects/2026/ata/backend/ArbitrageApi/Services/TradeService.cs",
                "region": {
                  "startLine": 194,
                  "startColumn": 13,
                  "endLine": 194,
                  "endColumn": 163
                }
              }
            }
          ],
          "properties": {
            "warningLevel": 1
          }
        },
        {
          "ruleId": "CA1873",
          "level": "note",
          "message": "Evaluation of this argument may be expensive and unnecessary if logging is disabled",
          "locations": [
            {
              "resultFile": {
                "uri": "file:///C:/Projects/2026/ata/backend/ArbitrageApi/Services/Exchanges/Coinbase/CoinbaseSandboxState.cs",
                "region": {
                  "startLine": 172,
                  "startColumn": 9,
                  "endLine": 172,
                  "endColumn": 140
                }
              }
            }
          ],
          "properties": {
            "warningLevel": 1
          }
        },
        {
          "ruleId": "CA1873",
          "level": "note",
          "message": "Evaluation of this argument may be expensive and unnecessary if logging is disabled",
          "locations": [
            {
              "resultFile": {
                "uri": "file:///C:/Projects/2026/ata/backend/ArbitrageApi/Services/Exchanges/Coinbase/CoinbaseSandboxState.cs",
                "region": {
                  "startLine": 202,
                  "startColumn": 9,
                  "endLine": 202,
                  "endColumn": 141
                }
              }
            }
          ],
          "properties": {
            "warningLevel": 1
          }
        },
        {
          "ruleId": "CA1873",
          "level": "note",
          "message": "Evaluation of this argument may be expensive and unnecessary if logging is disabled",
          "locations": [
            {
              "resultFile": {
                "uri": "file:///C:/Projects/2026/ata/backend/ArbitrageApi/Services/Exchanges/Coinbase/CoinbaseSandboxState.cs",
                "region": {
                  "startLine": 254,
                  "startColumn": 9,
                  "endLine": 254,
                  "endColumn": 78
                }
              }
            }
          ],
          "properties": {
            "warningLevel": 1
          }
        },
        {
          "ruleId": "CA1873",
          "level": "note",
          "message": "Evaluation of this argument may be expensive and unnecessary if logging is disabled",
          "locations": [
            {
              "resultFile": {
                "uri": "file:///C:/Projects/2026/ata/backend/ArbitrageApi/Services/ArbitrageDetectionService.cs",
                "region": {
                  "startLine": 257,
                  "startColumn": 17,
                  "endLine": 258,
                  "endColumn": 75
                }
              }
            }
          ],
          "properties": {
            "warningLevel": 1
          }
        },
        {
          "ruleId": "CA1873",
          "level": "note",
          "message": "Evaluation of this argument may be expensive and unnecessary if logging is disabled",
          "locations": [
            {
              "resultFile": {
                "uri": "file:///C:/Projects/2026/ata/backend/ArbitrageApi/Services/StatePersistenceService.cs",
                "region": {
                  "startLine": 52,
                  "startColumn": 21,
                  "endLine": 52,
                  "endColumn": 100
                }
              }
            }
          ],
          "properties": {
            "warningLevel": 1
          }
        },
        {
          "ruleId": "CA1872",
          "level": "note",
          "message": "Prefer 'System.Convert.ToHexStringLower(byte[])' over call chains based on 'System.BitConverter.ToString(byte[])'",
          "locations": [
            {
              "resultFile": {
                "uri": "file:///C:/Projects/2026/ata/backend/ArbitrageApi/Services/Exchanges/Coinbase/CoinbaseAdvancedTradeService.cs",
                "region": {
                  "startLine": 141,
                  "startColumn": 20,
                  "endLine": 141,
                  "endColumn": 76
                }
              }
            }
          ],
          "relatedLocations": [
            {
              "physicalLocation": {
                "uri": "file:///C:/Projects/2026/ata/backend/ArbitrageApi/Services/Exchanges/Coinbase/CoinbaseAdvancedTradeService.cs",
                "region": {
                  "startLine": 141,
                  "startColumn": 20,
                  "endLine": 141,
                  "endColumn": 49
                }
              }
            }
          ],
          "properties": {
            "warningLevel": 1,
            "customProperties": {
              "ReplacementPropertiesKey": "ToHexStringLower"
            }
          }
        },
        {
          "ruleId": "CA1861",
          "level": "note",
          "message": "Prefer 'static readonly' fields over constant array arguments if the called method is called repeatedly and is not mutating the passed array",
          "locations": [
            {
              "resultFile": {
                "uri": "file:///C:/Projects/2026/ata/backend/ArbitrageApi/Services/Exchanges/Coinbase/CoinbaseAdvancedTradeService.cs",
                "region": {
                  "startLine": 154,
                  "startColumn": 38,
                  "endLine": 154,
                  "endColumn": 66
                }
              }
            }
          ],
          "properties": {
            "warningLevel": 1,
            "customProperties": {
              "paramName": "separator"
            }
          }
        },
        {
          "ruleId": "CA1873",
          "level": "note",
          "message": "Evaluation of this argument may be expensive and unnecessary if logging is disabled",
          "locations": [
            {
              "resultFile": {
                "uri": "file:///C:/Projects/2026/ata/backend/ArbitrageApi/Services/Exchanges/Coinbase/CoinbaseSandboxState.cs",
                "region": {
                  "startLine": 244,
                  "startColumn": 9,
                  "endLine": 244,
                  "endColumn": 97
                }
              }
            }
          ],
          "properties": {
            "warningLevel": 1
          }
        },
        {
          "ruleId": "CA1873",
          "level": "note",
          "message": "Evaluation of this argument may be expensive and unnecessary if logging is disabled",
          "locations": [
            {
              "resultFile": {
                "uri": "file:///C:/Projects/2026/ata/backend/ArbitrageApi/Services/Exchanges/Binance/BinanceSandboxState.cs",
                "region": {
                  "startLine": 53,
                  "startColumn": 13,
                  "endLine": 54,
                  "endColumn": 46
                }
              }
            }
          ],
          "properties": {
            "warningLevel": 1
          }
        },
        {
          "ruleId": "CA1873",
          "level": "note",
          "message": "Evaluation of this argument may be expensive and unnecessary if logging is disabled",
          "locations": [
            {
              "resultFile": {
                "uri": "file:///C:/Projects/2026/ata/backend/ArbitrageApi/Services/Exchanges/Binance/BinanceSandboxState.cs",
                "region": {
                  "startLine": 90,
                  "startColumn": 13,
                  "endLine": 90,
                  "endColumn": 97
                }
              }
            }
          ],
          "properties": {
            "warningLevel": 1
          }
        },
        {
          "ruleId": "CA1873",
          "level": "note",
          "message": "Evaluation of this argument may be expensive and unnecessary if logging is disabled",
          "locations": [
            {
              "resultFile": {
                "uri": "file:///C:/Projects/2026/ata/backend/ArbitrageApi/Services/ArbitrageDetectionService.cs",
                "region": {
                  "startLine": 339,
                  "startColumn": 9,
                  "endLine": 339,
                  "endColumn": 114
                }
              }
            }
          ],
          "properties": {
            "warningLevel": 1
          }
        },
        {
          "ruleId": "CA1873",
          "level": "note",
          "message": "Evaluation of this argument may be expensive and unnecessary if logging is disabled",
          "locations": [
            {
              "resultFile": {
                "uri": "file:///C:/Projects/2026/ata/backend/ArbitrageApi/Services/ArbitrageDetectionService.cs",
                "region": {
                  "startLine": 350,
                  "startColumn": 17,
                  "endLine": 350,
                  "endColumn": 106
                }
              }
            }
          ],
          "properties": {
            "warningLevel": 1
          }
        },
        {
          "ruleId": "CA1873",
          "level": "note",
          "message": "Evaluation of this argument may be expensive and unnecessary if logging is disabled",
          "locations": [
            {
              "resultFile": {
                "uri": "file:///C:/Projects/2026/ata/backend/ArbitrageApi/Services/ArbitrageDetectionService.cs",
                "region": {
                  "startLine": 360,
                  "startColumn": 9,
                  "endLine": 360,
                  "endColumn": 87
                }
              }
            }
          ],
          "properties": {
            "warningLevel": 1
          }
        },
        {
          "ruleId": "CA1873",
          "level": "note",
          "message": "Evaluation of this argument may be expensive and unnecessary if logging is disabled",
          "locations": [
            {
              "resultFile": {
                "uri": "file:///C:/Projects/2026/ata/backend/ArbitrageApi/Services/Exchanges/Binance/BinanceSandboxState.cs",
                "region": {
                  "startLine": 170,
                  "startColumn": 9,
                  "endLine": 170,
                  "endColumn": 97
                }
              }
            }
          ],
          "properties": {
            "warningLevel": 1
          }
        },
        {
          "ruleId": "CA1873",
          "level": "note",
          "message": "Evaluation of this argument may be expensive and unnecessary if logging is disabled",
          "locations": [
            {
              "resultFile": {
                "uri": "file:///C:/Projects/2026/ata/backend/ArbitrageApi/Services/Exchanges/Coinbase/CoinbaseRealState.cs",
                "region": {
                  "startLine": 93,
                  "startColumn": 13,
                  "endLine": 93,
                  "endColumn": 90
                }
              }
            }
          ],
          "properties": {
            "warningLevel": 1
          }
        },
        {
          "ruleId": "CA1873",
          "level": "note",
          "message": "Evaluation of this argument may be expensive and unnecessary if logging is disabled",
          "locations": [
            {
              "resultFile": {
                "uri": "file:///C:/Projects/2026/ata/backend/ArbitrageApi/Services/Exchanges/Coinbase/CoinbaseClient.cs",
                "region": {
                  "startLine": 37,
                  "startColumn": 9,
                  "endLine": 37,
                  "endColumn": 94
                }
              }
            }
          ],
          "properties": {
            "warningLevel": 1
          }
        },
        {
          "ruleId": "CA1873",
          "level": "note",
          "message": "Evaluation of this argument may be expensive and unnecessary if logging is disabled",
          "locations": [
            {
              "resultFile": {
                "uri": "file:///C:/Projects/2026/ata/backend/ArbitrageApi/Services/Exchanges/Coinbase/CoinbaseClient.cs",
                "region": {
                  "startLine": 50,
                  "startColumn": 9,
                  "endLine": 50,
                  "endColumn": 97
                }
              }
            }
          ],
          "properties": {
            "warningLevel": 1
          }
        },
        {
          "ruleId": "CA1872",
          "level": "note",
          "message": "Prefer 'System.Convert.ToHexStringLower(byte[])' over call chains based on 'System.BitConverter.ToString(byte[])'",
          "locations": [
            {
              "resultFile": {
                "uri": "file:///C:/Projects/2026/ata/backend/ArbitrageApi/Services/Exchanges/Binance/BinanceBaseState.cs",
                "region": {
                  "startLine": 154,
                  "startColumn": 16,
                  "endLine": 154,
                  "endColumn": 70
                }
              }
            }
          ],
          "relatedLocations": [
            {
              "physicalLocation": {
                "uri": "file:///C:/Projects/2026/ata/backend/ArbitrageApi/Services/Exchanges/Binance/BinanceBaseState.cs",
                "region": {
                  "startLine": 154,
                  "startColumn": 16,
                  "endLine": 154,
                  "endColumn": 43
                }
              }
            }
          ],
          "properties": {
            "warningLevel": 1,
            "customProperties": {
              "ReplacementPropertiesKey": "ToHexStringLower"
            }
          }
        },
        {
          "ruleId": "CA2254",
          "level": "note",
          "message": "The logging message template should not vary between calls to 'LoggerExtensions.LogError(ILogger, string?, params object?[])'",
          "locations": [
            {
              "resultFile": {
                "uri": "file:///C:/Projects/2026/ata/backend/ArbitrageApi/Services/Exchanges/Coinbase/CoinbaseAdvancedTradeService.cs",
                "region": {
                  "startLine": 294,
                  "startColumn": 30,
                  "endLine": 294,
                  "endColumn": 85
                }
              }
            }
          ],
          "properties": {
            "warningLevel": 1
          }
        },
        {
          "ruleId": "CA1873",
          "level": "note",
          "message": "Evaluation of this argument may be expensive and unnecessary if logging is disabled",
          "locations": [
            {
              "resultFile": {
                "uri": "file:///C:/Projects/2026/ata/backend/ArbitrageApi/Services/Exchanges/Coinbase/CoinbaseBaseState.cs",
                "region": {
                  "startLine": 65,
                  "startColumn": 13,
                  "endLine": 65,
                  "endColumn": 95
                }
              }
            }
          ],
          "properties": {
            "warningLevel": 1
          }
        },
        {
          "ruleId": "CA1873",
          "level": "note",
          "message": "Evaluation of this argument may be expensive and unnecessary if logging is disabled",
          "locations": [
            {
              "resultFile": {
                "uri": "file:///C:/Projects/2026/ata/backend/ArbitrageApi/Services/Exchanges/Coinbase/CoinbaseBaseState.cs",
                "region": {
                  "startLine": 70,
                  "startColumn": 13,
                  "endLine": 70,
                  "endColumn": 88
                }
              }
            }
          ],
          "properties": {
            "warningLevel": 1
          }
        },
        {
          "ruleId": "CA1873",
          "level": "note",
          "message": "Evaluation of this argument may be expensive and unnecessary if logging is disabled",
          "locations": [
            {
              "resultFile": {
                "uri": "file:///C:/Projects/2026/ata/backend/ArbitrageApi/Services/Exchanges/Coinbase/CoinbaseBaseState.cs",
                "region": {
                  "startLine": 84,
                  "startColumn": 13,
                  "endLine": 84,
                  "endColumn": 84
                }
              }
            }
          ],
          "properties": {
            "warningLevel": 1
          }
        },
        {
          "ruleId": "CA1873",
          "level": "note",
          "message": "Evaluation of this argument may be expensive and unnecessary if logging is disabled",
          "locations": [
            {
              "resultFile": {
                "uri": "file:///C:/Projects/2026/ata/backend/ArbitrageApi/Services/Exchanges/Binance/BinanceBaseState.cs",
                "region": {
                  "startLine": 270,
                  "startColumn": 13,
                  "endLine": 271,
                  "endColumn": 93
                }
              }
            }
          ],
          "properties": {
            "warningLevel": 1
          }
        },
        {
          "ruleId": "CA1873",
          "level": "note",
          "message": "Evaluation of this argument may be expensive and unnecessary if logging is disabled",
          "locations": [
            {
              "resultFile": {
                "uri": "file:///C:/Projects/2026/ata/backend/ArbitrageApi/Services/Exchanges/Coinbase/CoinbaseAdvancedTradeService.cs",
                "region": {
                  "startLine": 420,
                  "startColumn": 10,
                  "endLine": 420,
                  "endColumn": 101
                }
              }
            }
          ],
          "properties": {
            "warningLevel": 1
          }
        },
        {
          "ruleId": "CA1873",
          "level": "note",
          "message": "Evaluation of this argument may be expensive and unnecessary if logging is disabled",
          "locations": [
            {
              "resultFile": {
                "uri": "file:///C:/Projects/2026/ata/backend/ArbitrageApi/Services/Exchanges/Binance/BinanceBaseState.cs",
                "region": {
                  "startLine": 354,
                  "startColumn": 17,
                  "endLine": 354,
                  "endColumn": 90
                }
              }
            }
          ],
          "properties": {
            "warningLevel": 1
          }
        },
        {
          "ruleId": "CA1822",
          "level": "note",
          "message": "Member 'MapBinanceStatus' does not access instance data and can be marked as static",
          "locations": [
            {
              "resultFile": {
                "uri": "file:///C:/Projects/2026/ata/backend/ArbitrageApi/Services/Exchanges/Binance/BinanceBaseState.cs",
                "region": {
                  "startLine": 368,
                  "startColumn": 32,
                  "endLine": 368,
                  "endColumn": 48
                }
              }
            }
          ],
          "properties": {
            "warningLevel": 1
          }
        },
        {
          "ruleId": "CA1822",
          "level": "note",
          "message": "Member 'FindBestPrices' does not access instance data and can be marked as static",
          "locations": [
            {
              "resultFile": {
                "uri": "file:///C:/Projects/2026/ata/backend/ArbitrageApi/Services/ArbitrageDetectionService.cs",
                "region": {
                  "startLine": 207,
                  "startColumn": 13,
                  "endLine": 207,
                  "endColumn": 27
                }
              }
            }
          ],
          "properties": {
            "warningLevel": 1
          }
        },
        {
          "ruleId": "CA1822",
          "level": "note",
          "message": "Member 'SimulateOrderBookExecution' does not access instance data and can be marked as static",
          "locations": [
            {
              "resultFile": {
                "uri": "file:///C:/Projects/2026/ata/backend/ArbitrageApi/Services/ArbitrageDetectionService.cs",
                "region": {
                  "startLine": 265,
                  "startColumn": 108,
                  "endLine": 265,
                  "endColumn": 134
                }
              }
            }
          ],
          "properties": {
            "warningLevel": 1
          }
        },
        {
          "ruleId": "CA1873",
          "level": "note",
          "message": "Evaluation of this argument may be expensive and unnecessary if logging is disabled",
          "locations": [
            {
              "resultFile": {
                "uri": "file:///C:/Projects/2026/ata/backend/ArbitrageApi/Services/Exchanges/Coinbase/CoinbaseBaseState.cs",
                "region": {
                  "startLine": 125,
                  "startColumn": 13,
                  "endLine": 125,
                  "endColumn": 88
                }
              }
            }
          ],
          "properties": {
            "warningLevel": 1
          }
        },
        {
          "ruleId": "CA1873",
          "level": "note",
          "message": "Evaluation of this argument may be expensive and unnecessary if logging is disabled",
          "locations": [
            {
              "resultFile": {
                "uri": "file:///C:/Projects/2026/ata/backend/ArbitrageApi/Services/Exchanges/Coinbase/CoinbaseBaseState.cs",
                "region": {
                  "startLine": 133,
                  "startColumn": 13,
                  "endLine": 133,
                  "endColumn": 122
                }
              }
            }
          ],
          "properties": {
            "warningLevel": 1
          }
        },
        {
          "ruleId": "CA1822",
          "level": "note",
          "message": "Member 'Base64UrlEncode' does not access instance data and can be marked as static",
          "locations": [
            {
              "resultFile": {
                "uri": "file:///C:/Projects/2026/ata/backend/ArbitrageApi/Services/Exchanges/Coinbase/CoinbaseAdvancedTradeService.cs",
                "region": {
                  "startLine": 124,
                  "startColumn": 22,
                  "endLine": 124,
                  "endColumn": 37
                }
              }
            }
          ],
          "properties": {
            "warningLevel": 1
          }
        },
        {
          "ruleId": "CA1822",
          "level": "note",
          "message": "Member 'GenerateRandomHex' does not access instance data and can be marked as static",
          "locations": [
            {
              "resultFile": {
                "uri": "file:///C:/Projects/2026/ata/backend/ArbitrageApi/Services/Exchanges/Coinbase/CoinbaseAdvancedTradeService.cs",
                "region": {
                  "startLine": 135,
                  "startColumn": 22,
                  "endLine": 135,
                  "endColumn": 39
                }
              }
            }
          ],
          "properties": {
            "warningLevel": 1
          }
        },
        {
          "ruleId": "CA1822",
          "level": "note",
          "message": "Member 'ExtractPrivateKeyFromPem' does not access instance data and can be marked as static",
          "locations": [
            {
              "resultFile": {
                "uri": "file:///C:/Projects/2026/ata/backend/ArbitrageApi/Services/Exchanges/Coinbase/CoinbaseAdvancedTradeService.cs",
                "region": {
                  "startLine": 149,
                  "startColumn": 22,
                  "endLine": 149,
                  "endColumn": 46
                }
              }
            }
          ],
          "properties": {
            "warningLevel": 1
          }
        }
      ],
      "rules": {
        "CA1050": {
          "id": "CA1050",
          "shortDescription": "Declare types in namespaces",
          "fullDescription": "Types are declared in namespaces to prevent name collisions and as a way to organize related types in an object hierarchy.",
          "defaultLevel": "note",
          "helpUri": "https://learn.microsoft.com/dotnet/fundamentals/code-analysis/quality-rules/ca1050",
          "properties": {
            "category": "Design",
            "isEnabledByDefault": true,
            "tags": [
              "PortedFromFxCop",
              "Telemetry",
              "EnabledRuleInAggressiveMode"
            ]
          }
        },
        "CA1822": {
          "id": "CA1822",
          "shortDescription": "Mark members as static",
          "fullDescription": "Members that do not access instance data or call instance methods can be marked as static. After you mark the methods as static, the compiler will emit nonvirtual call sites to these members. This can give you a measurable performance gain for performance-sensitive code.",
          "defaultLevel": "note",
          "helpUri": "https://learn.microsoft.com/dotnet/fundamentals/code-analysis/quality-rules/ca1822",
          "properties": {
            "category": "Performance",
            "isEnabledByDefault": true,
            "tags": [
              "PortedFromFxCop",
              "Telemetry",
              "EnabledRuleInAggressiveMode"
            ]
          }
        },
        "CA1860": {
          "id": "CA1860",
          "shortDescription": "Avoid using 'Enumerable.Any()' extension method",
          "fullDescription": "Prefer using 'IsEmpty', 'Count' or 'Length' properties whichever available, rather than calling 'Enumerable.Any()'. The intent is clearer and it is more performant than using 'Enumerable.Any()' extension method.",
          "defaultLevel": "note",
          "helpUri": "https://learn.microsoft.com/dotnet/fundamentals/code-analysis/quality-rules/ca1860",
          "properties": {
            "category": "Performance",
            "isEnabledByDefault": true,
            "tags": [
              "Telemetry",
              "EnabledRuleInAggressiveMode"
            ]
          }
        },
        "CA1861": {
          "id": "CA1861",
          "shortDescription": "Avoid constant arrays as arguments",
          "fullDescription": "Constant arrays passed as arguments are not reused when called repeatedly, which implies a new array is created each time. Consider extracting them to 'static readonly' fields to improve performance if the passed array is not mutated within the called method.",
          "defaultLevel": "note",
          "helpUri": "https://learn.microsoft.com/dotnet/fundamentals/code-analysis/quality-rules/ca1861",
          "properties": {
            "category": "Performance",
            "isEnabledByDefault": true,
            "tags": [
              "Telemetry",
              "EnabledRuleInAggressiveMode"
            ]
          }
        },
        "CA1869": {
          "id": "CA1869",
          "shortDescription": "Cache and reuse 'JsonSerializerOptions' instances",
          "fullDescription": "Avoid creating a new 'JsonSerializerOptions' instance for every serialization operation. Cache and reuse instances instead. Single use 'JsonSerializerOptions' instances can substantially degrade the performance of your application.",
          "defaultLevel": "note",
          "helpUri": "https://learn.microsoft.com/dotnet/fundamentals/code-analysis/quality-rules/ca1869",
          "properties": {
            "category": "Performance",
            "isEnabledByDefault": true,
            "tags": [
              "Telemetry",
              "EnabledRuleInAggressiveMode"
            ]
          }
        },
        "CA1872": {
          "id": "CA1872",
          "shortDescription": "Prefer 'Convert.ToHexString' and 'Convert.ToHexStringLower' over call chains based on 'BitConverter.ToString'",
          "fullDescription": "Use 'Convert.ToHexString' or 'Convert.ToHexStringLower' when encoding bytes to a hexadecimal string representation. These methods are more efficient and allocation-friendly than using 'BitConverter.ToString' in combination with 'String.Replace' to replace dashes and 'String.ToLower'.",
          "defaultLevel": "note",
          "helpUri": "https://learn.microsoft.com/dotnet/fundamentals/code-analysis/quality-rules/ca1872",
          "properties": {
            "category": "Performance",
            "isEnabledByDefault": true,
            "tags": [
              "Telemetry",
              "EnabledRuleInAggressiveMode"
            ]
          }
        },
        "CA1873": {
          "id": "CA1873",
          "shortDescription": "Avoid potentially expensive logging",
          "fullDescription": "In many situations, logging is disabled or set to a log level that results in an unnecessary evaluation for this argument.",
          "defaultLevel": "note",
          "helpUri": "https://learn.microsoft.com/dotnet/fundamentals/code-analysis/quality-rules/ca1873",
          "properties": {
            "category": "Performance",
            "isEnabledByDefault": true,
            "tags": [
              "Telemetry",
              "EnabledRuleInAggressiveMode"
            ]
          }
        },
        "CA2254": {
          "id": "CA2254",
          "shortDescription": "Template should be a static expression",
          "fullDescription": "The logging message template should not vary between calls.",
          "defaultLevel": "note",
          "helpUri": "https://learn.microsoft.com/dotnet/fundamentals/code-analysis/quality-rules/ca2254",
          "properties": {
            "category": "Usage",
            "isEnabledByDefault": true,
            "tags": [
              "Telemetry",
              "EnabledRuleInAggressiveMode"
            ]
          }
        },
        "CS1061": {
          "id": "CS1061",
          "defaultLevel": "error",
          "helpUri": "https://msdn.microsoft.com/query/roslyn.query?appId=roslyn&k=k(CS1061)",
          "properties": {
            "category": "Compiler",
            "isEnabledByDefault": true,
            "tags": [
              "Compiler",
              "Telemetry",
              "NotConfigurable"
            ]
          }
        },
        "CS8603": {
          "id": "CS8603",
          "shortDescription": "Possible null reference return.",
          "defaultLevel": "warning",
          "helpUri": "https://msdn.microsoft.com/query/roslyn.query?appId=roslyn&k=k(CS8603)",
          "properties": {
            "category": "Compiler",
            "isEnabledByDefault": true,
            "tags": [
              "Compiler",
              "Telemetry"
            ]
          }
        },
        "CS8618": {
          "id": "CS8618",
          "shortDescription": "Non-nullable field must contain a non-null value when exiting constructor. Consider adding the 'required' modifier or declaring as nullable.",
          "defaultLevel": "warning",
          "helpUri": "https://msdn.microsoft.com/query/roslyn.query?appId=roslyn&k=k(CS8618)",
          "properties": {
            "category": "Compiler",
            "isEnabledByDefault": true,
            "tags": [
              "Compiler",
              "Telemetry"
            ]
          }
        },
        "SYSLIB0023": {
          "id": "SYSLIB0023",
          "shortDescription": "Type or member is obsolete",
          "defaultLevel": "warning",
          "helpUri": "https://aka.ms/dotnet-warnings/SYSLIB0023",
          "properties": {
            "category": "Compiler",
            "isEnabledByDefault": true,
            "tags": [
              "Compiler",
              "Telemetry",
              "CustomObsolete"
            ]
          }
        }
      }
    }
  ]
}